sprofile/__init__.py
sprofile/sprofile.py
sprofile-0.2.3.dist-info/LICENSE.txt
sprofile-0.2.3.dist-info/METADATA
sprofile-0.2.3.dist-info/WHEEL
sprofile-0.2.3.dist-info/entry_points.txt
sprofile-0.2.3.dist-info/top_level.txt
sprofile-0.2.3.dist-info/RECORD
