Metadata-Version: 2.2
Name: sprofile
Version: 0.2.3
Summary: Reporting tool for resources actually consumed by a SLURM job.
Author-email: Nicolas Granger <nicolas.granger@cea.fr>
License: CECILL-C
Keywords: hpc,slurm,profiling,optimization,cgroups
Classifier: Programming Language :: Python :: 3
Classifier: License :: CeCILL-C Free Software License Agreement (CECILL-C)
Classifier: Topic :: System :: Clustering
Classifier: Intended Audience :: Science/Research
Classifier: Intended Audience :: System Administrators
Classifier: Topic :: System :: Clustering
License-File: LICENSE.txt
Requires-Dist: nvidia-ml-py
